Workbook

Sheet Dashboard
A1: AKE Project Tracking System
A2: Design Thinking + Spiral Model | AKE SAP B1 Training Database | Tracker Dashboard (V1)
A4: VERSION | C4: OVERALL % COMPLETE | E4: BOTTLENECK STAGE | G4: TOPICS TRACKED
A5: ='AKE Tracking System V1'!AH2 -> 1 | C5: ='AKE Tracking System V1'!AH7 -> 0.35555556 | E5: =INDEX($A$11:$A$15,MATCH(MIN($E$11:$E$15),$E$11:$E$15,0)) -> Prototype | G5: =COUNTIF('AKE Tracking System V1'!$B$2:$B$200,"Closed")+COUNTIF('AKE Tracking System V1'!$B$2:$B$200,"Open") -> 18
A9: PROGRESS BY PHASE
A10: Stage | B10: Closed | C10: Open | D10: Total | E10: % Complete
A11: Empathise | B11: =COUNTIF('AKE Tracking System V1'!B2:B200,"Closed") -> 18 | C11: =COUNTIF('AKE Tracking System V1'!B2:B200,"Open") -> 0 | D11: =B11+C11 -> 18 | E11: =IF(D11=0,0,B11/D11) -> 1
A12: Define | B12: =COUNTIF('AKE Tracking System V1'!H2:H200,"Closed") -> 5 | C12: =COUNTIF('AKE Tracking System V1'!H2:H200,"Open") -> 13 | D12: =B12+C12 -> 18 | E12: =IF(D12=0,0,B12/D12) -> 0.27777778
A13: Ideate | B13: =COUNTIF('AKE Tracking System V1'!N2:N200,"Closed") -> 9 | C13: =COUNTIF('AKE Tracking System V1'!N2:N200,"Open") -> 9 | D13: =B13+C13 -> 18 | E13: =IF(D13=0,0,B13/D13) -> 0.5
A14: Prototype | B14: =COUNTIF('AKE Tracking System V1'!U2:U200,"Closed") -> 0 | C14: =COUNTIF('AKE Tracking System V1'!U2:U200,"Open") -> 18 | D14: =B14+C14 -> 18 | E14: =IF(D14=0,0,B14/D14) -> 0
A15: Testing | B15: =COUNTIF('AKE Tracking System V1'!AA2:AA200,"Closed") -> 0 | C15: =COUNTIF('AKE Tracking System V1'!AA2:AA200,"Open") -> 18 | D15: =B15+C15 -> 18 | E15: =IF(D15=0,0,B15/D15) -> 0
A22: Closed (all phases) | B22: =SUM(B11:B15) -> 32
A23: Open (all phases) | B23: =SUM(C11:C15) -> 58
A42: HOW TO READ THIS DASHBOARD
A43: • Version and Overall % Complete pull live from the Iteration Info block on the main sheet - no manual updates needed.
A44: • Bottleneck Stage highlights whichever phase has the lowest % Complete right now, so you always know where attention is needed.
A45: • The phase table and both charts recalculate automatically as topics move from Open to Closed on the main sheet.

Sheet AKE Tracking System V1
A1: Section / Topic | B1: ="Empathise Version (V"&$AH$2&" - Open/Closed)" -> Empathise Version (V1 - Open/Closed) | C1: Details | D1: Responsibility | E1: Target Date | F1: Attachments | H1: ="Define Version (V"&$AH$2&" - Open/Closed)" -> Define Version (V1 - Open/Closed) | I1: Details | J1: Responsibility | K1: Target Date | L1: Attachments | N1: ="Ideate Version (V"&$AH$2&" - Open/Closed)" -> Ideate Version (V1 - Open/Closed) | O1: Details | P1: Risk / Assumption | Q1: Responsibility | R1: Target Date | S1: Attachments | U1: ="Prototype Version (V"&$AH$2&" - Open/Closed)" -> Prototype Version (V1 - Open/Closed) | V1: Details | W1: Responsibility | X1: Target Date | Y1: Attachments | AA1: ="Testing Version (V"&$AH$2&" - Open/Closed)" -> Testing Version (V1 - Open/Closed) | AB1: Details | AC1: Responsibility | AD1: Target Date | AE1: Attachments | AG1: Iteration Info
A2: A. Customer & Training Scope | AG2: Version | AH2: 1
A3: A1. Customer Profile & Business Model | B3: Closed | C3: AKE Infrastructure Pvt. Ltd. (akeinfra.com) - Qltc customer for 5+ years, on SAP B1 (SQL) for 5 years. Design document describes them as a fabrication company; environment section says Infrastructure / Construction / Engineering Projects. Working model agreed: steel-structure fabricator (plates, structurals, TMT, special grades) that also executes project work - confirmed by AKE's own item groups (RM Plates, RM Structurals, Machining, Rolling) and job-work expense heads (Blasting & Primer, Galvanizing, Fabrication & Erection) in their Chart of Accounts. | D3: Qltc Consultant / Claude | E3: 46296 | H3: Open | I3: TBD | N3: Open | O3: TBD | U3: Open | V3: TBD | AA3: Open | AB3: TBD | AG3: Objective | AH3: Build and validate a complete SAP B1 10 (HANA, India, INR) training database for AKE Infrastructure Pvt. Ltd. covering OTC, PTP, Production to Stock, Finance, Inventory and Resources - using AKE's real COA, GST + TDS, dummy items/BPs, and never exposing real selling prices.
A4: A2. Training Participants & Roles | B4: Closed | C4: Rashmi and Namrata - Directors; Ashok - Planning, SCM; Sunil - Finance; Veena - Accounts. Current users are new to SAP B1 - the earlier super users trained by Qltc have left AKE. | D4: Qltc Consultant | E4: 46296 | H4: Open | I4: TBD | N4: Open | O4: TBD | U4: Open | V4: TBD | AA4: Open | AB4: TBD | AG4: Owner | AH4: Qltc Consultant
A5: A3. Training Schedule & Module Scope | B5: Closed | C5: 3 days: Mon 5 Oct - Wed 7 Oct 2026. Scope: OTC (Order to Cash), PTP (Procure to Pay), PTS = Production to Stock (BOM -> Production Order -> Issue for Production -> Receipt from Production -> Stock) - confirmed by Qltc 1 Oct 2026, NOT plan-to-stock. Also Finance, Inventory, Resources. | D5: Qltc Consultant | E5: 46296 | H5: Open | I5: TBD | N5: Open | O5: TBD | U5: Open | V5: TBD | AA5: Open | AB5: TBD | AG5: Start Date | AH5: 46296
A6: A4. SAP Environment | B6: Closed | C6: SAP Business One 10.0 for SAP HANA, version 10.00.310, FP 2511 (64-bit), India localization, INR - confirmed from 'About SAP Business One' screenshot (Screenshot (1).png). Client host SSO-WINDOWS1. OPEN POINT: the About box shows the licence is issued to 'Bangalore Biotech Labs Private Limited', not AKE or Qltc - Qltc to confirm this is the right server and that the licence permits an AKE training company. | D6: Qltc Consultant | E6: 46296 | F6: Screenshot (1).png | H6: Closed | I6: Target build: B1 10.0 FP 2511 (10.00.310) on HANA. All DTW templates, Service Layer payloads and SQL checks built for this version. | J6: Qltc Consultant / Claude | K6: 46296 | N6: Open | O6: TBD | U6: Open | V6: TBD | AA6: Open | AB6: TBD | AG6: Target Date | AH6: 46296
A7: A5. Selling Price Confidentiality | B7: Closed | C7: Management does not want trainees to know item selling prices. Hard constraint for every training screen, report and demo document. | D7: Qltc Consultant | E7: 46296 | H7: Open | I7: DRAFT: Trainees must be able to run OTC end-to-end without ever seeing a real selling price. Success = no real price visible in price lists, item master, sales documents, gross profit window or reports under any trainee login. | J7: Qltc Consultant / Claude | K7: 46296 | N7: Closed | O7: Chosen: both layers - only dummy sales prices exist in the DB ('Sales Price (Dummy - Restricted)' price list, FG items only) + No Authorization on Price Lists, Gross Profit and Sales Analysis for all users except TRAINER. | P7: Authorizations are set manually - Service Layer cannot set general authorizations. | Q7: Qltc Consultant / Claude | R7: 46296 | U7: Open | V7: Built: price lists + dummy FG prices in data package; authorization settings in checklist Step 7. Awaiting load and SUNIL-login test. | W7: Qltc Consultant / Claude | X7: 46296 | Y7: tools/build_data.py -> data/*.json; tools/sl_loader.py; docs/01_Company_Setup_Checklist.md | AA7: Open | AB7: TBD | AG7: Overall % Complete | AH7: =IF((COUNTIF(B2:B23,"Closed")+COUNTIF(B2:B23,"Open")+COUNTIF(H2:H23,"Closed")+COUNTIF(H2:H23,"Open")+COUNTIF(N2:N23,"Closed")+COUNTIF(N2:N23,"Open")+COUNTIF(U2:U23,"Closed")+COUNTIF(U2:U23,"Open")+COUNTIF(AA2:AA23,"Closed")+COUNTIF(AA2:AA23,"Open"))=0,0,(COUNTIF(B2:B23,"Closed")+COUNTIF(H2:H23,"Closed")+COUNTIF(N2:N23,"Closed")+COUNTIF(U2:U23,"Closed")+COUNTIF(AA2:AA23,"Closed"))/(COUNTIF(B2:B23,"Closed")+COUNTIF(B2:B23,"Open")+COUNTIF(H2:H23,"Closed")+COUNTIF(H2:H23,"Open")+COUNTIF(N2:N23,"Closed")+COUNTIF(N2:N23,"Open")+COUNTIF(U2:U23,"Closed")+COUNTIF(U2:U23,"Open")+COUNTIF(AA2:AA23,"Closed")+COUNTIF(AA2:AA23,"Open"))) -> 0.35555556
A8: B. AKE Pain Points | AG8: Training Start | AH8: 46300
A9: B1. Inventory Not Matching Physical Stock | B9: Closed | C9: Answers (Qltc, 1 Oct 2026): most item groups AND warehouses mismatch; Issue for Production is done MANUALLY; GRPO is posted when goods arrive (purchase items); Receipt from Production is posted for produced items. Supporting COA evidence: 10 blank inventory group accounts, WIP held in two accounts (5002-01-01-15 and 5002-01-02). | D9: Qltc Consultant / Claude | E9: 46296 | H9: Open | I9: DRAFT: Ashok needs system stock to equal physical stock in every warehouse. With manual Issue for Production, components are issued late, partially or in wrong quantities (and with wrong BOM quantities - see B3), so stock drifts while GRPO/Receipt keep adding to it. Training must show: correct issue against a production order, warehouse-wise stock check, Inventory Counting and Posting to correct differences. | J9: Qltc Consultant / Claude | K9: 46296 | N9: Closed | O9: Chosen: 6 clear warehouses (RM-STR, CONS, SHOP, FG, SCRAP, SITE), manual Issue for Production kept (AKE's real practice), Block negative inventory = Yes, dummy opening stock per warehouse, Inventory Counting exercise in training. | Q9: Qltc Consultant / Claude | R9: 46296 | U9: Open | V9: Built: warehouses, items with manual issue method, opening stock (30 lines). Awaiting load. | W9: Qltc Consultant / Claude | X9: 46296 | Y9: tools/build_data.py -> data/*.json; tools/sl_loader.py; docs/01_Company_Setup_Checklist.md | AA9: Open | AB9: TBD
A10: B2. Finance Reports Not Coming Properly | B10: Closed | C10: Root causes found in AKE's real Chart of Accounts (598 accounts) - see 'COA Findings' sheet: 34 liability-coded (3002-xx) lender/loan accounts sit in the ASSET drawer under 5002-05-06 Others; the same loans are duplicated in Liabilities (e.g. Kotak LAP 19510148, Kotak LAP 19404642, Deutsche Bank 0037, JSW One Finance); 36 accounts have no name; 10 orphan accounts; 2 malformed codes; GST payable split across 3002-03 / 3002-09 / 3003-09; TDS Payable spread over 14 accounts. | D10: Qltc Consultant / Claude | E10: 46296 | F10: COA Findings sheet; Chart of Accounts *.csv | H10: Open | I10: DRAFT: Sunil and Veena need a Balance Sheet and P&L they can trust. Today loans show as negative assets, duplicated loan accounts split balances, and GST/TDS liabilities are scattered - so no report can be correct whatever the user does. | J10: Qltc Consultant / Claude | K10: 46296 | N10: Open | O10: TBD | U10: Open | V10: TBD | AA10: Open | AB10: TBD
A11: B3. BOM Needs Correction | B11: Closed | C11: Answers (Qltc, 1 Oct 2026): BOM quantities do not match reality - wrong quantity entries on BOM lines. Training DB will use dummy fabrication BOMs with realistic quantities (weight-based steel: kg per unit), plus one deliberately wrong BOM to demonstrate the effect. | D11: Qltc Consultant | E11: 46296 | H11: Open | I11: DRAFT: Wrong BOM quantities make every production order issue the wrong components, so stock and product cost are wrong even when users follow the process. Training must show how a wrong BOM quantity flows into Issue for Production, stock and cost - and how to correct it. | J11: Qltc Consultant / Claude | K11: 46296 | N11: Closed | O11: Chosen: 5 production BOMs with realistic steel weights (e.g. ISMB300 6m column = 265.2 kg) incl. resources; the 'wrong BOM' (2652 kg decimal slip) is a live trainer exercise, not loaded. | Q11: Qltc Consultant / Claude | R11: 46296 | U11: Open | V11: Built: 09_boms.json (2 sub-assemblies, 3 FG). Awaiting load. | W11: Qltc Consultant / Claude | X11: 46296 | Y11: tools/build_data.py -> data/*.json; tools/sl_loader.py; docs/01_Company_Setup_Checklist.md | AA11: Open | AB11: TBD
A12: B4. Users Not Aware of SAP B1 | B12: Closed | C12: Earlier super-user training was given but those users left; current users are new. Training must be hands-on, role-based and follow AKE's real processes, with step-by-step exercises per participant. | D12: Qltc Consultant | E12: 46296 | H12: Open | I12: TBD | N12: Open | O12: TBD | U12: Open | V12: TBD | AA12: Open | AB12: TBD
A13: C. Database Configuration & Data
A14: C1. Chart of Accounts - AKE Real | B14: Closed | C14: Decision (Qltc, 1 Oct 2026): use AKE's real Chart of Accounts, not the standard India template, and use it to show AKE the finance report problems. Export received as 5 files (Asset 199, Liability 122, Equity 12, Revenue 37, Expenditure 228 accounts) and pushed to GitHub. | D14: Qltc Consultant | E14: 46296 | F14: COA Findings sheet; Chart of Accounts *.csv | H14: Closed | I14: Decision (Qltc, 1 Oct 2026): load AKE's Chart of Accounts EXACTLY as given (as-is, all 598 accounts), so trainees see their own structure and the COA Findings can be demonstrated live in the Finance session. Corrections are shown, not pre-applied. | J14: Qltc Consultant | K14: 46296 | N14: Closed | O14: Chosen: load 598 accounts as given. Parents rebuilt from codes + file order (export lost indentation); 42 placed by position; 36 blank names get placeholder '(No name in AKE COA) <code>' because B1 requires a name. | P14: Placement of 42 accounts is reconstructed - verify against OACT (FatherNum, Levels) from AKE's SQL DB if exact tree matters. | Q14: Qltc Consultant / Claude | R14: 46296 | U14: Open | V14: Built: 01_chart_of_accounts.json + 01_coa_placement_review.json. Dry-run OK (598 posts). Awaiting load. | W14: Qltc Consultant / Claude | X14: 46296 | Y14: tools/build_data.py -> data/*.json; tools/sl_loader.py; docs/01_Company_Setup_Checklist.md | AA14: Open | AB14: TBD
A15: C2. Tax - GST and TDS (No e-Invoice) | B15: Closed | C15: Decision (Qltc, 1 Oct 2026): GST + TDS required; e-Invoice out of scope. Note: TDS is not written in the design document - recorded here as Qltc's instruction. AKE already uses TDS @0.75%, 1%, 1.5%, 2%, 7.5%, 10%, on Rent, Professional, Purchases (194Q) and Interest. | D15: Qltc Consultant | E15: 46296 | H15: Open | I15: TBD | N15: Closed | O15: Chosen: 4 GST codes (CGST+SGST / IGST at 18% and 12%) and 6 TDS codes (194Q, 194C1, 194C2, 194J, 194I, 194A) on AKE's existing accounts. | P15: India tax setup is manual - not loaded via Service Layer. | Q15: Qltc Consultant / Claude | R15: 46296 | U15: Open | V15: Built: 07_gst_codes.json, 07_tds_codes.json; setup in checklist Steps 5-6 (manual). HSN per item in data package. | W15: Qltc Consultant / Claude | X15: 46296 | Y15: tools/build_data.py -> data/*.json; tools/sl_loader.py; docs/01_Company_Setup_Checklist.md | AA15: Open | AB15: TBD
A16: C3. Master Data - Realistic Dummy Items & BPs | B16: Closed | C16: Decision (Qltc, 1 Oct 2026): realistic dummy data, not AKE's live masters. Items follow AKE's own item groups (RM Plates, RM Structurals, RM Special Grades, TMT Rod, Consumables, Tools, PPE, Sub Assembly, FG). Indian vendors and customers with dummy GSTIN/PAN. | D16: Qltc Consultant | E16: 46296 | H16: Open | I16: TBD | N16: Closed | O16: Chosen: 37 dummy items across AKE's 9 item groups; 9 fictional vendors + 6 fictional customers in KA/TN/MH/TS/KL with checksum-valid dummy GSTIN. | Q16: Qltc Consultant / Claude | R16: 46296 | U16: Open | V16: Built: 05_items.json, 06_business_partners.json. Dry-run OK. Awaiting load. | W16: Qltc Consultant / Claude | X16: 46296 | Y16: tools/build_data.py -> data/*.json; tools/sl_loader.py; docs/01_Company_Setup_Checklist.md | AA16: Open | AB16: TBD
A17: C4. Opening Balances & Posting Periods | B17: Closed | C17: Decision (Qltc, 1 Oct 2026): use DUMMY opening balances (stock, BP, GL). Financial year assumed FY 2026-27 (Apr 2026 - Mar 2027), monthly posting periods. | D17: Qltc Consultant | E17: 46296 | H17: Closed | I17: Opening balances: dummy stock per item/warehouse, dummy BP balances, dummy GL balances against 1003 Opening Balance Offset Account. | J17: Qltc Consultant / Claude | K17: 46296 | N17: Closed | O17: Chosen: opening date 01-Apr-2026 against 1003 Opening Balance Offset Account - stock via Goods Receipt, BP and GL via Journal Entries. | Q17: Qltc Consultant / Claude | R17: 46296 | U17: Open | V17: Built: 11_opening_balances.json (30 stock lines, 6 BP, 10 GL). Awaiting load. | W17: Qltc Consultant / Claude | X17: 46296 | Y17: tools/build_data.py -> data/*.json; tools/sl_loader.py; docs/01_Company_Setup_Checklist.md | AA17: Open | AB17: TBD
A18: C5. Users, Licences & Authorizations | B18: Closed | C18: Decision (Qltc, 1 Oct 2026): 6 user licences - Rashmi, Namrata, Ashok, Sunil, Veena + trainer (manager). Licence type not yet stated (assume Professional). | D18: Qltc Consultant | E18: 46296 | H18: Closed | I18: 6 users, role-based authorizations; selling prices hidden for all trainee users (A5). | J18: Qltc Consultant / Claude | K18: 46296 | N18: Closed | O18: Chosen: 6 users (TRAINER superuser), role matrix in checklist Step 7; licences assigned manually. | Q18: Qltc Consultant / Claude | R18: 46296 | U18: Open | V18: Built: 10_users.json; passwords from git-ignored .env. Awaiting load. | W18: Qltc Consultant / Claude | X18: 46296 | Y18: tools/build_data.py -> data/*.json; tools/sl_loader.py; docs/01_Company_Setup_Checklist.md | AA18: Open | AB18: TBD
A19: D. Method & Delivery
A20: D1. Design Thinking + Spiral Model | B20: Closed | C20: Qltc method (Qltc_Design_Thinking_Spiral_Model_Training.pptx): Empathize+Define -> Q1 Objectives; Ideate -> Q1/Q2 Alternatives; Prototype -> Q2/Q3 Risk & Build; Test -> Q4 Review & plan next loop. Followed regardless of deadline pressure. | D20: Qltc Consultant | E20: 46296 | F20: Qltc_Design_Thinking_Spiral_Model_Training.pptx | H20: Open | I20: TBD | N20: Open | O20: TBD | U20: Open | V20: TBD | AA20: Open | AB20: TBD
A21: D2. Deadline | B21: Closed | C21: Database ready for Qltc testing by 1 Oct 2026 afternoon; demo/training from Mon 5 Oct 2026. | D21: Qltc Consultant | E21: 46296 | H21: Open | I21: TBD | N21: Open | O21: TBD | U21: Open | V21: TBD | AA21: Open | AB21: TBD
A22: D3. Delivery Mechanism - Access to SAP | B22: Closed | C22: Decision (Qltc, 1 Oct 2026): Qltc will provide Service Layer access - data will be posted directly by Claude. Credentials to be kept in a local, git-ignored file - never committed to the public repo. Pending: Service Layer URL, company DB name, user. | D22: Qltc Consultant / Claude | E22: 46296 | H22: Closed | I22: Loader posts all masters and opening balances through Service Layer; Qltc creates the empty company and does the manual setup steps (G/L determination, GST, TDS, licences, authorizations). | J22: Qltc Consultant / Claude | K22: 46296 | N22: Closed | O22: Chosen: idempotent Python loader (skips existing records, logs every call), dry-run mode, credentials only in .env. | Q22: Qltc Consultant / Claude | R22: 46296 | U22: Open | V22: Built and dry-run tested (all 13 steps). Not yet run against the server - expect a short fix-and-rerun loop on first contact. | W22: Qltc Consultant / Claude | X22: 46296 | Y22: tools/build_data.py -> data/*.json; tools/sl_loader.py; docs/01_Company_Setup_Checklist.md | AA22: Open | AB22: TBD
A23: D4. Source Control | B23: Closed | C23: All project files kept in GitHub repo reetha-qltc/AKE-Database (public - confirmed by Qltc, including AKE COA files). | D23: Qltc Consultant / Claude | E23: 46296 | H23: Open | I23: TBD | N23: Open | O23: TBD | U23: Open | V23: TBD | AA23: Open | AB23: TBD

Sheet COA Findings
A1: AKE Chart of Accounts - Findings (Spiral 1, Empathise/Define evidence for topic B2)
A2: Source: AKE's real Chart of Accounts export (5 CSV files, 598 accounts), analysed 1 Oct 2026.
A4: ID | B4: Issue Type | C4: Severity | D4: Accounts Affected | E4: Finding | F4: Impact on Reports | G4: Session / Audience | H4: Proposed Correction
A5: F01 | B5: Wrong drawer | C5: High | D5: 5002-05-06 Others (Asset drawer) | E5: 34 accounts with liability codes 3002-xx (private lenders, NBFCs, Kotak/Deutsche Bank loans, JSW One Finance) are created in the ASSET drawer. | F5: Loans appear as negative current assets; Balance Sheet understates both assets and liabilities. | G5: Sunil, Veena | H5: Move to Liabilities > 3002-07 Other Finances / 3002-01 Secured Loans; then lock 5002-05-06.
A6: F02 | B6: Duplicate loan accounts | C6: High | D6: 3002-01-12 & 3002-01-15; 3002-01-10 & 3002-01-16; 3002-01-14 & 3002-01-18; 3002-01-13 & 3002-01-13-01 | E6: Same Kotak LAP, Deutsche Bank and JSW One Finance loans exist in more than one account (one of each pair in the Asset drawer or under Non-Current). A further 'Deutsche bank Loan A/c' (3002-02-06-08) sits under Trade Creditors - which loan it belongs to is unclear. | F6: Loan balances split across accounts - outstanding loan per lender cannot be read from any one report. | G6: Sunil, Veena | H6: One GL per loan; JE to merge balances; deactivate duplicates.
A7: F03 | B7: Duplicate bank account | C7: High | D7: 5002-02-02-04 & 3002-01-11 | E7: Kotak current account exists as a bank (asset) and again under 3002-01 Secured Loans codes. | F7: Bank reconciliation and cash position wrong. | G7: Veena | H7: Keep 5002-02-02-04; merge and deactivate 3002-01-11.
A8: F04 | B8: Blank account names | C8: Medium | D8: 36 accounts (19 Asset, 7 Liability, 2 Revenue, 8 Expenditure) | E8: Accounts with codes but no name, e.g. 5002-01-01-14, -19, -21..-29 (inventory groups), 3002-03-02/05/07/08, 2003-07, 4004-07-14/31. | F8: Users cannot pick the right account; postings to unnamed accounts are invisible in reports. | G8: Sunil, Veena | H8: Name or deactivate; remove from training COA.
A9: F05 | B9: Orphan accounts (parent missing) | C9: Medium | D9: 1001-01-01-01..03; 3003-09-03..08; 5002-04-07-01 | E9: Share capital per shareholder has no 1001-01-01 parent; GST output/RCM payables coded 3003-09-xx sit under 3002-09 GST Payable; Advance Clearing coded 5002-04-07-01 sits under 5002-04-04. | F9: Account codes do not match their position in the tree - grouping in Trial Balance and Balance Sheet is unreliable. | G9: Sunil | H9: Re-code to match parent (e.g. 3002-09-03..08).
A10: F06 | B10: Malformed codes | C10: Low | D10: 3002007-35 Kumar Arts; 4004-4-08 Medical Insurance | E10: Codes break the segment pattern (missing hyphen / single-digit segment). Kumar Arts also exists correctly as 3002-07-35. | F10: Sorting and code-based reports misplace these accounts. | G10: Veena | H10: Merge Kumar Arts; re-code 4004-04-08.
A11: F07 | B11: GST payable scattered | C11: High | D11: 3002-03-22/24/25/27; 3002-09-01/02; 3003-09-03..08 | E11: IGST/CGST/SGST payable exist in Statutory Payables AND in GST Payable, with a separate 'GST PAYABLE' 3002-03-27. | F11: GST liability report never matches GSTR-3B; tax determination may post to different accounts. | G11: Sunil, Veena | H11: One output account per tax type under 3002-09; map in Tax Code determination.
A12: F08 | B12: TDS payable spread over 14 accounts | C12: High | D12: 3002-03-03, -04, -10..-16, -18, -20, -21, -23, -26 | E12: TDS split by rate AND by nature with overlaps: 'TDS on Rent' (3002-03-13) and 'TDS Payable on Rent' (3002-03-15); 1% / 2% / 0.75% / 1.5% rate accounts alongside section-wise ones. | F12: TDS payable per section (for challan/return) cannot be reported. Directly relevant to the TDS setup in the training DB. | G12: Sunil, Veena | H12: One account per TDS section (194C, 194J, 194I, 194Q, 194A, 192) mapped to Withholding Tax codes.
A13: F09 | B13: Duplicate WIP accounts | C13: Medium | D13: 5002-01-01-15 & 5002-01-02 | E13: Work-in-progress exists as an item-group account and as a separate WIP account. | F13: Production WIP split - production cost reports and inventory valuation disagree. Links to B1 inventory mismatch. | G13: Ashok, Sunil | H13: Use one WIP account in G/L account determination (Production).
A14: F10 | B14: Duplicate expense heads | C14: Medium | D14: Rates & Taxes x4; Audit Fees x3; Professional Tax, Electrical Inspection, KIADB in both 4002 and 4004; LWF-MGT x2 | E14: Same expense exists under Manufacturing (4002) and Administrative (4004) expenses, or twice in the same group. | F14: Same cost posted to different heads - P&L by function is inconsistent between periods. | G14: Sunil | H14: Keep one per function; deactivate the rest.
A15: F11 | B15: Misclassified accounts | C15: Medium | D15: 5002-05-04-03 Suspense A/C; 5002-05-04-01 Income Tax Refund (under Investments); 3003-02 Conversion Expenses (under Provisions); 4004-07-22 Sale of FA Asset (under Expenses) | E15: Accounts sit under groups that do not describe them. | F15: Balance Sheet groups (Investments, Provisions) are overstated/misleading. | G15: Sunil | H15: Re-parent to the correct group.
... A18: F14 | B18: Product sales posted to an unnamed account | C18: High | D18: 2001-01-01 SALES-PRODUCT SALES; 2001-01-01-01 (no name) | E18: 2001-01-01 is a title account; its only postable child 2001-01-01-01 has no name. Product sales revenue can only be posted to the unnamed account. | F18: The main revenue line of the P&L appears without a name; sales analysis by GL is unreadable. | G18: Sunil, Veena | H18: Name 2001-01-01-01 'Sales - Product Sales (Domestic)' and use it in G/L determination.
A20: Summary
B21: High | C21: =COUNTIF($C$5:$C$18,B21) -> 6
B22: Medium | C22: =COUNTIF($C$5:$C$18,B22) -> 5
B23: Low | C23: =COUNTIF($C$5:$C$18,B23) -> 3

Sheet How To Use
A1: How to use this tracker (V1)
A3: This tracker follows the Qltc Project Tracking System format: each topic moves through Empathise -> Define -> Ideate -> Prototype -> Testing, each stage Open or Closed.
A4: Spiral mapping (Qltc method deck): Empathise + Define = Q1 Determine Objectives; Ideate = Q1/Q2 Alternatives; Prototype = Q2/Q3 Resolve Risk & Build; Testing = Q4 Review & Plan Next Loop.
A5: Topics are grouped into 4 sections: A) Customer & Training Scope, B) AKE Pain Points, C) Database Configuration & Data, D) Method & Delivery.
A6: Empathise topics marked Closed carry answers already confirmed by Qltc on 1 Oct 2026. Open Empathise topics are genuine gaps that need answers before Spiral 1 can close.
A7: Define cells starting with 'DRAFT:' are proposed problem statements written by Claude - Qltc reviews and changes the status to Closed when agreed.
A8: The 'COA Findings' sheet is the evidence behind topic B2 (Finance reports) and will be used in Sunil and Veena's Finance session.
A9: Status cells have a drop-down (Open / Closed); the Dashboard recalculates automatically.
